MANIFEST.in
README.txt
setup.py
docs/HISTORY.txt
docs/LICENSE.txt
src/infrae/__init__.py
src/infrae.testbrowser.egg-info/PKG-INFO
src/infrae.testbrowser.egg-info/SOURCES.txt
src/infrae.testbrowser.egg-info/dependency_links.txt
src/infrae.testbrowser.egg-info/namespace_packages.txt
src/infrae.testbrowser.egg-info/not-zip-safe
src/infrae.testbrowser.egg-info/requires.txt
src/infrae.testbrowser.egg-info/top_level.txt
src/infrae/testbrowser/__init__.py
src/infrae/testbrowser/browser.py
src/infrae/testbrowser/cookies.py
src/infrae/testbrowser/expressions.py
src/infrae/testbrowser/form.py
src/infrae/testbrowser/headers.py
src/infrae/testbrowser/interfaces.py
src/infrae/testbrowser/python26.py
src/infrae/testbrowser/utils.py
src/infrae/testbrowser/wsgi.py
src/infrae/testbrowser/selenium/__init__.py
src/infrae/testbrowser/selenium/browser.py
src/infrae/testbrowser/selenium/cookies.py
src/infrae/testbrowser/selenium/driver.py
src/infrae/testbrowser/selenium/errors.py
src/infrae/testbrowser/selenium/expressions.py
src/infrae/testbrowser/selenium/form.py
src/infrae/testbrowser/selenium/server.py
src/infrae/testbrowser/selenium/utils.py
src/infrae/testbrowser/selenium/tests/__init__.py
src/infrae/testbrowser/selenium/tests/test_browsing.py
src/infrae/testbrowser/selenium/tests/test_expressions.py
src/infrae/testbrowser/selenium/tests/test_form.py
src/infrae/testbrowser/tests/__init__.py
src/infrae/testbrowser/tests/app.py
src/infrae/testbrowser/tests/browser.py
src/infrae/testbrowser/tests/expressions.py
src/infrae/testbrowser/tests/form.py
src/infrae/testbrowser/tests/test_browsing.py
src/infrae/testbrowser/tests/test_expressions.py
src/infrae/testbrowser/tests/test_form.py
src/infrae/testbrowser/tests/test_headers.py
src/infrae/testbrowser/tests/test_utils.py
src/infrae/testbrowser/tests/data/button_form.html
src/infrae/testbrowser/tests/data/checkbox_form.html
src/infrae/testbrowser/tests/data/default_form.html
src/infrae/testbrowser/tests/data/file_form.html
src/infrae/testbrowser/tests/data/link_expressions.html
src/infrae/testbrowser/tests/data/lxml_regression.html
src/infrae/testbrowser/tests/data/malformed_form.html
src/infrae/testbrowser/tests/data/multi_hidden_form.html
src/infrae/testbrowser/tests/data/multi_mixed_form.html
src/infrae/testbrowser/tests/data/multicheckbox_form.html
