Metadata-Version: 1.0
Name: infrae.testbrowser
Version: 2.0.2
Summary: Sane functionnal test browser for WSGI applications
Home-page: http://infrae.com/products/silva
Author: Infrae
Author-email: info@infrae.com
License: BSD
Keywords: test wsgi application functional
Platform: UNKNOWN
Classifier: License :: OSI Approved :: BSD License
Classifier: Programming Language :: Python
Classifier: Topic :: Software Development :: Libraries :: Python Modules
